fker/__init__.py
fker/yk.py
fker-1.0.dist-info/LICENSE
fker-1.0.dist-info/METADATA
fker-1.0.dist-info/WHEEL
fker-1.0.dist-info/top_level.txt
fker-1.0.dist-info/RECORD
