Metadata-Version: 2.1
Name: fker
Version: 1.0
Summary: 一个非常NB的包
Author: yk-_0
Author-email: yk-_0@live.com
Classifier: Programming Language :: Python :: 3
Classifier: License :: OSI Approved :: MIT License
Classifier: Operating System :: OS Independent
Requires-Python: >=3
License-File: LICENSE
Requires-Dist: pillow
